glis/__init__.py
glis/rbf.py
glis/solvers.py
glis-2.0.2.dist-info/LICENSE.txt
glis-2.0.2.dist-info/METADATA
glis-2.0.2.dist-info/WHEEL
glis-2.0.2.dist-info/top_level.txt
glis-2.0.2.dist-info/RECORD
