Metadata-Version: 2.1
Name: glis
Version: 2.0.2
Summary: GLIS - (GL)obal optimization by (I)nverse distance weighting and (S)urrogate radial basis functions
Author-email: Alberto Bemporad <alberto.bemporad@imtlucca.it>, Mengjia Zhu <mengjia.zhu@imtlucca.it>
Project-URL: Homepage, http://cse.lab.imtlucca.it/~bemporad/glis
Keywords: global optimization,preference-based optimization,black-box optimization
Classifier: Programming Language :: Python :: 3
Classifier: License :: OSI Approved :: Apache Software License
Classifier: Operating System :: OS Independent
Requires-Python: >=3.7
License-File: LICENSE.txt
Requires-Dist: numpy
Requires-Dist: scipy
Requires-Dist: pyswarm
Requires-Dist: pydoe
Requires-Dist: numba
